pynpm/__init__.py
pynpm/package.py
pynpm/utils.py
pynpm-0.2.0.dist-info/AUTHORS.rst
pynpm-0.2.0.dist-info/LICENSE
pynpm-0.2.0.dist-info/METADATA
pynpm-0.2.0.dist-info/WHEEL
pynpm-0.2.0.dist-info/top_level.txt
pynpm-0.2.0.dist-info/RECORD
