Metadata-Version: 2.1
Name: pynpm
Version: 0.2.0
Summary: "Python interface to your NPM and package.json."
Home-page: https://github.com/inveniosoftware/pynpm
Author: CERN
Author-email: info@inveniosoftware.org
License: BSD
Keywords: npm node package.json
Platform: any
Classifier: Development Status :: 5 - Production/Stable
Requires-Python: >=3.7
Provides-Extra: tests
Provides-Extra: docs
